cyberpandas/__init__.py
cyberpandas/_accessor.py
cyberpandas/_utils.py
cyberpandas/base.py
cyberpandas/common.py
cyberpandas/dtypes.py
cyberpandas/ip_array.py
cyberpandas/ip_methods.py
cyberpandas/mac_array.py
cyberpandas/parser.py
cyberpandas-1.1.1.dist-info/METADATA
cyberpandas-1.1.1.dist-info/RECORD
cyberpandas-1.1.1.dist-info/WHEEL
cyberpandas-1.1.1.dist-info/top_level.txt
tests/__init__.py
tests/ip/__init__.py
tests/ip/test_dtypes.py
tests/ip/test_interface.py
tests/ip/test_ip.py
tests/ip/test_ip_pandas.py
tests/ip/test_pandas_methods.py
tests/ip/test_parser.py
tests/mac/__init__.py
tests/mac/test_interface.py
