Metadata-Version: 2.1
Name: cyberpandas
Version: 1.1.1
Summary: IP Address type for pandas
Home-page: https://github.com/ContinuumIO/cyberpandas
Author: Tom Augspurger
Author-email: tom.w.augspurger@gmail.com
License: BSD
Platform: UNKNOWN
Classifier: License :: OSI Approved :: BSD License
Classifier: Programming Language :: Python :: 2
Classifier: Programming Language :: Python :: 2.7
Classifier: Programming Language :: Python :: 3
Classifier: Programming Language :: Python :: 3.5
Classifier: Programming Language :: Python :: 3.6
Requires-Dist: pandas (>=0.23.0)
Requires-Dist: six
Requires-Dist: ipaddress; python_version < "3"
